odoo/addons/stock_barcodes_picking_batch_revision/README.rst
odoo/addons/stock_barcodes_picking_batch_revision/__init__.py
odoo/addons/stock_barcodes_picking_batch_revision/__manifest__.py
odoo/addons/stock_barcodes_picking_batch_revision/data/stock_barcodes_action.xml
odoo/addons/stock_barcodes_picking_batch_revision/i18n/es.po
odoo/addons/stock_barcodes_picking_batch_revision/i18n/stock_barcodes_picking_batch_revision.pot
odoo/addons/stock_barcodes_picking_batch_revision/models/__init__.py
odoo/addons/stock_barcodes_picking_batch_revision/models/stock_move_line.py
odoo/addons/stock_barcodes_picking_batch_revision/models/stock_picking_batch.py
odoo/addons/stock_barcodes_picking_batch_revision/readme/CONTRIBUTORS.rst
odoo/addons/stock_barcodes_picking_batch_revision/readme/DESCRIPTION.rst
odoo/addons/stock_barcodes_picking_batch_revision/readme/USAGE.rst
odoo/addons/stock_barcodes_picking_batch_revision/static/description/icon.png
odoo/addons/stock_barcodes_picking_batch_revision/static/description/index.html
odoo/addons/stock_barcodes_picking_batch_revision/static/src/js/boolean_toggle_big.js
odoo/addons/stock_barcodes_picking_batch_revision/static/src/scss/boolean_toggle_big.scss
odoo/addons/stock_barcodes_picking_batch_revision/views/stock_picking_batch_views.xml
odoo/addons/stock_barcodes_picking_batch_revision/wizard/__init__.py
odoo/addons/stock_barcodes_picking_batch_revision/wizard/stock_barcodes_read_picking_batch.py
odoo/addons/stock_barcodes_picking_batch_revision/wizard/stock_barcodes_read_picking_batch_views.xml
odoo/addons/stock_barcodes_picking_batch_revision/wizard/stock_barcodes_read_todo.py
odoo_addon_stock_barcodes_picking_batch_revision-15.0.1.0.1.dist-info/METADATA
odoo_addon_stock_barcodes_picking_batch_revision-15.0.1.0.1.dist-info/WHEEL
odoo_addon_stock_barcodes_picking_batch_revision-15.0.1.0.1.dist-info/top_level.txt
odoo_addon_stock_barcodes_picking_batch_revision-15.0.1.0.1.dist-info/RECORD
